azdocli/__init__.py
azdocli/azdocli.py
azdocli/strategy_sample.py
azdocli/lib/__init__.py
azdocli/lib/commons.py
azdocli/lib/controller_switch.py
azdocli/lib/core.py
azdocli/lib/exceptions.py
azdocli/lib/pipelines.py
azdocli/strategies/__init__.py
azdocli/strategies/pipelineruns_get_strategy.py
azdocli/strategies/projects_get_strategy.py
azdocli/strategies/projects_list_strategy.py
azdocli/strategies/strategy_context.py
azdocli/strategies/svc_list_strategy.py
azdocli/strategies/teams_get_strategy.py
azdocli/strategies/teams_list_strategy.py
tests/__init__.py
tests/test_azdocli.py
tests/lib/__init__.py
tests/lib/test_commons.py
tests_integration/__init__.py
tests_integration/test_integration_project.py
azdo_cli-1.0.1.dist-info/LICENSE
azdo_cli-1.0.1.dist-info/METADATA
azdo_cli-1.0.1.dist-info/WHEEL
azdo_cli-1.0.1.dist-info/entry_points.txt
azdo_cli-1.0.1.dist-info/top_level.txt
azdo_cli-1.0.1.dist-info/RECORD
