Metadata-Version: 2.1
Name: azdo-cli
Version: 1.0.1
Summary: An Azure DevOps CLI client.
Home-page: https://github.com/migzpogi/azdo-cli
Author: Migz Estrella
Author-email: me@migzestrella.com
License: UNKNOWN
Platform: UNKNOWN
Classifier: Programming Language :: Python :: 3
Classifier: License :: OSI Approved :: MIT License
Classifier: Operating System :: OS Independent
Requires-Python: >=3.6
License-File: LICENSE
Requires-Dist: Click
